{
    "header": {
        "comments": null,
        "description": "camera spectral sensitivity data",
        "document_creation_date": "2025-06-03T10:59:08.091496Z",
        "document_creator": "wetadigital",
        "laboratory": "wetadigital",
        "license": "Apache-2.0",
        "manufacturer": "Canon",
        "measurement_equipment": "lightsaber",
        "model": "EOS 100D",
        "schema_version": "0.1.0",
        "unique_identifier": "20d08640-eaa1-484e-8455-c047a9d62068"
    },
    "spectral_data": {
        "bandwidth_FWHM": null,
        "bandwidth_corrected": null,
        "data": {
            "main": {
                "380": [
                    0.000998306326927055,
                    0.001305476291483759,
                    0.00113478489382237
                ],
                "385": [
                    0.001027389383228288,
                    0.0012306820562458058,
                    0.0016228945614096334
                ],
                "390": [
                    0.001056472439529525,
                    0.001155887821007854,
                    0.0021110042289968936
                ],
                "395": [
                    0.0010855554958307588,
                    0.001081093585769904,
                    0.0025991138965841603
                ],
                "400": [
                    0.0017544857041849318,
                    0.0020865652392110107,
                    0.011398518563864252
                ],
                "405": [
                    0.002423415912539107,
                    0.0030920368926521157,
                    0.02019792323114432
                ],
                "410": [
                    0.009403043751958376,
                    0.017750508438691383,
                    0.15673529641563622
                ],
                "415": [
                    0.016516600154217746,
                    0.03822769536660181,
                    0.3557076019482405
                ],
                "420": [
                    0.019300300572455516,
                    0.05768875930256235,
                    0.5631707585499619
                ],
                "425": [
                    0.013427052124163914,
                    0.05865253881839377,
                    0.6215946781152972
                ],
                "430": [
                    0.009037871361106387,
                    0.06377762885626745,
                    0.6715697615203925
                ],
                "435": [
                    0.00687479212589996,
                    0.07514468467720407,
                    0.7088715906851282
                ],
                "440": [
                    0.004711712890693546,
                    0.08651174049814078,
                    0.7461734198498637
                ],
                "445": [
                    0.004069445734101809,
                    0.09553256269845972,
                    0.7823345494290985
                ],
                "450": [
                    0.003807381597163748,
                    0.10396682649362433,
                    0.8182105041119591
                ],
                "455": [
                    0.004649805166159444,
                    0.12014502412379234,
                    0.8196365268357231
                ],
                "460": [
                    0.005492228735155141,
                    0.1363232217539608,
                    0.821062549559489
                ],
                "465": [
                    0.009225152009533997,
                    0.2293136434269498,
                    0.8176703901960338
                ],
                "470": [
                    0.012958075283912867,
                    0.3223040650999391,
                    0.8142782308325811
                ],
                "475": [
                    0.018078816123197075,
                    0.43053013651443395,
                    0.7878327923361431
                ],
                "480": [
                    0.023546511353707646,
                    0.5425651203643054,
                    0.7556240340564602
                ],
                "485": [
                    0.028416328122701583,
                    0.6104199014135104,
                    0.7066662862920418
                ],
                "490": [
                    0.033952245990716605,
                    0.6778073526503549,
                    0.6547980795428248
                ],
                "495": [
                    0.04215256825481586,
                    0.7433254846377617,
                    0.5912880368544053
                ],
                "500": [
                    0.050352890518915096,
                    0.8088436166251673,
                    0.5277779941659868
                ],
                "505": [
                    0.0630279002960284,
                    0.857564859607096,
                    0.45565991069319794
                ],
                "510": [
                    0.07570291007314175,
                    0.9062861025890259,
                    0.38354182722041036
                ],
                "515": [
                    0.08635504737608529,
                    0.9381168774978299,
                    0.31861634682230067
                ],
                "520": [
                    0.09700718467902872,
                    0.969947652406635,
                    0.2536908664241919
                ],
                "525": [
                    0.10687052619367113,
                    0.9815062476348513,
                    0.21505922115273612
                ],
                "530": [
                    0.11673386770831325,
                    0.993064842863069,
                    0.17642757588127994
                ],
                "535": [
                    0.13182273496522182,
                    0.993519160825865,
                    0.14446010463421632
                ],
                "540": [
                    0.15543192607684767,
                    0.9743628489250582,
                    0.12356146210311311
                ],
                "545": [
                    0.18176925815374537,
                    0.9433896811623722,
                    0.10695309028949712
                ],
                "550": [
                    0.20810659023064285,
                    0.9124165133996863,
                    0.09034471847588116
                ],
                "555": [
                    0.24066529669804754,
                    0.8730354711710917,
                    0.07432972157067867
                ],
                "560": [
                    0.27569808583924904,
                    0.8321488146963435,
                    0.06160230734448514
                ],
                "565": [
                    0.31444199899114544,
                    0.7890037368523656,
                    0.05380626713680514
                ],
                "570": [
                    0.3783388688037414,
                    0.7322143447331632,
                    0.04839139693020721
                ],
                "575": [
                    0.45900437639013675,
                    0.6663287430971442,
                    0.04456397339099732
                ],
                "580": [
                    0.5320118175159905,
                    0.6013557388791928,
                    0.040933063542121756
                ],
                "585": [
                    0.5743869927996783,
                    0.5400331243335112,
                    0.03808820845458345
                ],
                "590": [
                    0.6099521221433123,
                    0.4734508751789305,
                    0.034813918675814515
                ],
                "595": [
                    0.6182770677267259,
                    0.38583008758875736,
                    0.029821890132123347
                ],
                "600": [
                    0.6196691994732866,
                    0.3018247454945406,
                    0.025021194512504865
                ],
                "605": [
                    0.5933300758724338,
                    0.23228118538415113,
                    0.020985830589176895
                ],
                "610": [
                    0.5641248092961522,
                    0.17548415719676422,
                    0.017688327634394502
                ],
                "615": [
                    0.5306203282567269,
                    0.137806926893882,
                    0.015497616132430551
                ],
                "620": [
                    0.49711584721730273,
                    0.10012969659099955,
                    0.013306904630466592
                ],
                "625": [
                    0.4590444002593305,
                    0.08454643066310269,
                    0.012651752135393159
                ],
                "630": [
                    0.42097295330135887,
                    0.06896316473520596,
                    0.01199659964031973
                ],
                "635": [
                    0.3806281880256603,
                    0.055732825726877266,
                    0.011850752433856148
                ],
                "640": [
                    0.3394031757702932,
                    0.04671506646588204,
                    0.012478545709924016
                ],
                "645": [
                    0.3082970855026104,
                    0.04043006467681059,
                    0.013145069184458527
                ],
                "650": [
                    0.2775397382154759,
                    0.03476349615461529,
                    0.013705176283577038
                ],
                "655": [
                    0.24817736285053843,
                    0.03157066069992503,
                    0.013839617881031488
                ],
                "660": [
                    0.21906257299329476,
                    0.028952755996806655,
                    0.01388062362920796
                ],
                "665": [
                    0.1909381251668289,
                    0.028634574299976377,
                    0.01354788598027257
                ],
                "670": [
                    0.15418300446965544,
                    0.026204631016159975,
                    0.012010504128826366
                ],
                "675": [
                    0.10448187446642049,
                    0.020607045351864348,
                    0.00866615597361394
                ],
                "680": [
                    0.06306924778491532,
                    0.014219955482347382,
                    0.005561085832108208
                ],
                "685": [
                    0.02718228998456304,
                    0.00730652947601613,
                    0.0026155343664069275
                ],
                "690": [
                    0.015910490007039892,
                    0.0048907934002600795,
                    0.001656192437888506
                ],
                "695": [
                    0.010792479485224006,
                    0.003599479807147843,
                    0.0011934028936658033
                ],
                "700": [
                    0.005674468963408167,
                    0.002308166214035596,
                    0.0007306133494430975
                ],
                "705": [
                    0.004739537039581941,
                    0.001954606771499499,
                    0.0006205158127117881
                ],
                "710": [
                    0.0038046051157557266,
                    0.0016010473289634003,
                    0.000510418275980479
                ],
                "715": [
                    0.0028696731919295067,
                    0.0012474878864273007,
                    0.0004003207392491693
                ],
                "720": [
                    0.0019347412681032905,
                    0.0008939284438912019,
                    0.0002902232025178595
                ],
                "725": [
                    0.0009998093442770725,
                    0.0005403690013551031,
                    0.00018012566578655057
                ],
                "730": [
                    0.00025186380521609867,
                    0.0002575214473262241,
                    9.204763640150301e-05
                ],
                "735": [
                    0.0002518638052160986,
                    0.0002575214473262241,
                    9.204763640150302e-05
                ],
                "740": [
                    0.0002518638052160986,
                    0.0002575214473262241,
                    9.204763640150302e-05
                ],
                "745": [
                    0.0002518638052160986,
                    0.0002575214473262241,
                    9.204763640150302e-05
                ],
                "750": [
                    0.0002518638052160986,
                    0.0002575214473262241,
                    9.204763640150302e-05
                ],
                "755": [
                    0.0002518638052160986,
                    0.0002575214473262241,
                    9.204763640150302e-05
                ],
                "760": [
                    0.0002518638052160986,
                    0.0002575214473262241,
                    9.204763640150302e-05
                ],
                "765": [
                    0.0002518638052160986,
                    0.0002575214473262241,
                    9.204763640150302e-05
                ],
                "770": [
                    0.0002518638052160986,
                    0.0002575214473262241,
                    9.204763640150302e-05
                ],
                "775": [
                    0.0002518638052160986,
                    0.0002575214473262241,
                    9.204763640150302e-05
                ],
                "780": [
                    0.0002518638052160986,
                    0.0002575214473262241,
                    9.204763640150302e-05
                ]
            }
        },
        "index": {
            "main": [
                "R",
                "G",
                "B"
            ]
        },
        "reflection_geometry": null,
        "transmission_geometry": null,
        "units": "relative"
    }
}
