{
    "header": {
        "schema_version": "0.1.0",
        "manufacturer": "Nikon",
        "model": "D5300",
        "description": "camera spectral sensitivity data",
        "document_creator": "wetadigital",
        "document_creation_date": "2025-11-10 00:07:43Z",
        "measurement_equipment": "lightsaber",
        "license": "Apache-2.0"
    },
    "spectral_data": {
        "units": "relative",
        "index": {
            "main": [
                "R",
                "G",
                "B"
            ]
        },
        "data": {
            "main": {
                "380": [
                    0.00047017146063389227,
                    0.00044765779733700655,
                    0.0012015750997732754
                ],
                "385": [
                    0.0009403429212677845,
                    0.0008953155946740131,
                    0.002403150199546551
                ],
                "390": [
                    0.0014105143819016768,
                    0.0013429733920110195,
                    0.0036047252993198268
                ],
                "395": [
                    0.001971802106672991,
                    0.0019490634853503144,
                    0.0059867664312002605
                ],
                "400": [
                    0.002897554887993994,
                    0.0031888827626987627,
                    0.013090671691509327
                ],
                "405": [
                    0.003823307669314997,
                    0.004428702040047212,
                    0.02019457695181839
                ],
                "410": [
                    0.0049564552724695446,
                    0.006425867727893494,
                    0.033074374263056476
                ],
                "415": [
                    0.009415578736898538,
                    0.015849705429480346,
                    0.08720573673031501
                ],
                "420": [
                    0.0188636659932392,
                    0.036413551151678054,
                    0.20321444693160418
                ],
                "425": [
                    0.03724201645722527,
                    0.08906303278072786,
                    0.49072239618065444
                ],
                "430": [
                    0.05562036692121133,
                    0.14171251440977767,
                    0.7782303454297046
                ],
                "435": [
                    0.05031177836246313,
                    0.16161153092403363,
                    0.8500249942832804
                ],
                "440": [
                    0.045003189803714934,
                    0.1815105474382896,
                    0.9218196431368562
                ],
                "445": [
                    0.04061764078228099,
                    0.1932065876240135,
                    0.9524279609828983
                ],
                "450": [
                    0.03623209176084706,
                    0.2049026278097374,
                    0.9830362788289403
                ],
                "455": [
                    0.03414029822904707,
                    0.23388166986412795,
                    0.9915181394144701
                ],
                "460": [
                    0.03204850469724708,
                    0.2628607119185185,
                    1.0
                ],
                "465": [
                    0.035573941464455514,
                    0.3334259850558737,
                    0.99541146499462
                ],
                "470": [
                    0.03909937823166394,
                    0.4039912581932289,
                    0.9908229299892402
                ],
                "475": [
                    0.04117210816975602,
                    0.43934088782744674,
                    0.9539157902741504
                ],
                "480": [
                    0.043244838107848085,
                    0.4746905174616646,
                    0.9170086505590609
                ],
                "485": [
                    0.04016849473852609,
                    0.4916107985942027,
                    0.8391107376720726
                ],
                "490": [
                    0.038754062327734734,
                    0.5261060381115649,
                    0.7572244889461194
                ],
                "495": [
                    0.03983249635473935,
                    0.5869637152061632,
                    0.6693557364617195
                ],
                "500": [
                    0.040910930381743975,
                    0.6478213923007613,
                    0.5814869839773197
                ],
                "505": [
                    0.04894194838006128,
                    0.742311472650629,
                    0.48979532308686574
                ],
                "510": [
                    0.05697296637837859,
                    0.8368015530004966,
                    0.39810366219641186
                ],
                "515": [
                    0.0741285792630663,
                    0.8916857121005439,
                    0.3239557542923187
                ],
                "520": [
                    0.09128419214775403,
                    0.9465698712005913,
                    0.24980784638822554
                ],
                "525": [
                    0.0971811815382299,
                    0.9708232966959331,
                    0.20612554405899214
                ],
                "530": [
                    0.10307817092870575,
                    0.9950767221912751,
                    0.16244324172975874
                ],
                "535": [
                    0.09381423940559656,
                    0.9947431256027472,
                    0.13290219634585207
                ],
                "540": [
                    0.07444302727343066,
                    0.9780181809583064,
                    0.11278865559216324
                ],
                "545": [
                    0.057964225884009214,
                    0.9374287568433277,
                    0.09010519893530368
                ],
                "550": [
                    0.04148542449458776,
                    0.896839332728349,
                    0.06742174227844411
                ],
                "555": [
                    0.03918368982238632,
                    0.8469504996333318,
                    0.05305424334006354
                ],
                "560": [
                    0.03688195515018487,
                    0.7970616665383146,
                    0.03868674440168296
                ],
                "565": [
                    0.04379276553867313,
                    0.7274410045574664,
                    0.02891326227042301
                ],
                "570": [
                    0.10795240639039953,
                    0.6550018614978145,
                    0.021642223496410654
                ],
                "575": [
                    0.25798529293698313,
                    0.5783349968199568,
                    0.018124849758269702
                ],
                "580": [
                    0.4080181794835668,
                    0.5016681321420993,
                    0.01460747602012875
                ],
                "585": [
                    0.5928355961263145,
                    0.425782727484445,
                    0.012474930959219708
                ],
                "590": [
                    0.7362640012926771,
                    0.3518238645000151,
                    0.010393602866276693
                ],
                "595": [
                    0.7141363605534996,
                    0.28557116820848255,
                    0.0085171426451978
                ],
                "600": [
                    0.6920087198143223,
                    0.21931847191694995,
                    0.006640682424118905
                ],
                "605": [
                    0.6447462392091938,
                    0.1712357219186344,
                    0.005775647920085506
                ],
                "610": [
                    0.5974837586040652,
                    0.12315297192031888,
                    0.004910613416052109
                ],
                "615": [
                    0.5361475027212745,
                    0.09506442723840462,
                    0.004516334423584732
                ],
                "620": [
                    0.4748112468384839,
                    0.0669758825564904,
                    0.004122055431117355
                ],
                "625": [
                    0.42268080059368895,
                    0.05588404254027157,
                    0.004269081408652048
                ],
                "630": [
                    0.370550354348894,
                    0.04479220252405274,
                    0.00441610738618674
                ],
                "635": [
                    0.326687714463393,
                    0.03766727253972951,
                    0.004921755991169909
                ],
                "640": [
                    0.288336945484088,
                    0.033186949243336664,
                    0.005666486347785396
                ],
                "645": [
                    0.2515430587491869,
                    0.028623958331551777,
                    0.0061526457037944585
                ],
                "650": [
                    0.2147491720142858,
                    0.024060967419766884,
                    0.006638805059803521
                ],
                "655": [
                    0.1801133275026286,
                    0.021143552337228866,
                    0.006636190748989023
                ],
                "660": [
                    0.14547748299097138,
                    0.018226137254690845,
                    0.006633576438174524
                ],
                "665": [
                    0.10959884068077817,
                    0.014770031814832416,
                    0.005366843942448994
                ],
                "670": [
                    0.07372019837058498,
                    0.011313926374973988,
                    0.004100111446723465
                ],
                "675": [
                    0.04429615554929434,
                    0.007496909228435832,
                    0.0026579224165694405
                ],
                "680": [
                    0.01648576260022936,
                    0.0035896641552277436,
                    0.0011718692528082928
                ],
                "685": [
                    0.010743157516722888,
                    0.002575821154173569,
                    0.0007990145464198768
                ],
                "690": [
                    0.005000552433216418,
                    0.001561978153119395,
                    0.0004261598400314607
                ],
                "695": [
                    0.003521371527729886,
                    0.0012699816760079327,
                    0.00035188861649747055
                ],
                "700": [
                    0.0020421906222433546,
                    0.00097798519889647,
                    0.00027761739296348046
                ],
                "705": [
                    0.0017590189051357973,
                    0.0008573526699221098,
                    0.0002451596091833447
                ],
                "710": [
                    0.00147584718802824,
                    0.0007367201409477496,
                    0.00021270182540320895
                ],
                "715": [
                    0.0011926754709206827,
                    0.0006160876119733893,
                    0.00018024404162307324
                ],
                "720": [
                    0.0009095037538131254,
                    0.000495455082999029,
                    0.0001477862578429375
                ],
                "725": [
                    0.0006263320367055683,
                    0.0003748225540246687,
                    0.00011532847406280174
                ],
                "730": [
                    0.00034316031959801083,
                    0.00025419002505030835,
                    8.287069028266601e-05
                ],
                "735": [
                    0.00034316031959801083,
                    0.00025419002505030835,
                    8.287069028266601e-05
                ],
                "740": [
                    0.00034316031959801083,
                    0.00025419002505030835,
                    8.287069028266601e-05
                ],
                "745": [
                    0.00034316031959801083,
                    0.00025419002505030835,
                    8.287069028266601e-05
                ],
                "750": [
                    0.00034316031959801083,
                    0.00025419002505030835,
                    8.287069028266601e-05
                ],
                "755": [
                    0.00034316031959801083,
                    0.00025419002505030835,
                    8.287069028266601e-05
                ],
                "760": [
                    0.00034316031959801083,
                    0.00025419002505030835,
                    8.287069028266601e-05
                ],
                "765": [
                    0.00034316031959801083,
                    0.00025419002505030835,
                    8.287069028266601e-05
                ],
                "770": [
                    0.00034316031959801083,
                    0.00025419002505030835,
                    8.287069028266601e-05
                ],
                "775": [
                    0.00034316031959801083,
                    0.00025419002505030835,
                    8.287069028266601e-05
                ],
                "780": [
                    0.00034316031959801083,
                    0.00025419002505030835,
                    8.287069028266601e-05
                ]
            }
        }
    }
}