{
    "header": {
        "comments": null,
        "description": "camera spectral sensitivity data",
        "document_creation_date": "2025-06-07T00:28:37.640284Z",
        "document_creator": "wetadigital",
        "laboratory": "wetadigital",
        "license": "Apache-2.0",
        "manufacturer": "Panasonic",
        "measurement_equipment": "lightsaber",
        "model": "DC-GX9",
        "schema_version": "0.1.0",
        "unique_identifier": "8d3d0d29-81f5-4f4d-b523-7cebdcbaa1cf"
    },
    "spectral_data": {
        "bandwidth_FWHM": null,
        "bandwidth_corrected": null,
        "data": {
            "main": {
                "380": [
                    0.0007783764999277946,
                    0.0013889359983244197,
                    0.000574811663283387
                ],
                "385": [
                    0.0007100767443504332,
                    0.0012065048159887782,
                    0.0006653704137815309
                ],
                "390": [
                    0.0006417769887730707,
                    0.0010240736336531357,
                    0.0007559291642796744
                ],
                "395": [
                    0.0005734772331957091,
                    0.0008416424513174946,
                    0.000846487914777818
                ],
                "400": [
                    0.0007448848469742255,
                    0.0011280935679754134,
                    0.0018368319444150927
                ],
                "405": [
                    0.0009162924607527449,
                    0.001414544684633333,
                    0.0028271759740523673
                ],
                "410": [
                    0.0013430043356778985,
                    0.002028886212757389,
                    0.006432875432229251
                ],
                "415": [
                    0.0029474457173323016,
                    0.005417168240690159,
                    0.02110366925994068
                ],
                "420": [
                    0.010086925299374163,
                    0.023512735804046114,
                    0.09607408538637542
                ],
                "425": [
                    0.032683137034310215,
                    0.08428563812744186,
                    0.34977545763330514
                ],
                "430": [
                    0.0463834725984728,
                    0.12896405556592558,
                    0.5252817713235358
                ],
                "435": [
                    0.046739993906474944,
                    0.14950074567704186,
                    0.5834954971787171
                ],
                "440": [
                    0.047096515214477136,
                    0.1700374357881581,
                    0.6417092230338987
                ],
                "445": [
                    0.04616898999133772,
                    0.19303475618705726,
                    0.6962978416841104
                ],
                "450": [
                    0.044920453135412805,
                    0.21664723415790205,
                    0.7499801835330788
                ],
                "455": [
                    0.04503208843312553,
                    0.24567241645299728,
                    0.755016109094314
                ],
                "460": [
                    0.04514372373083828,
                    0.2746975987480923,
                    0.7600520346555505
                ],
                "465": [
                    0.04910969708947027,
                    0.33885544055222844,
                    0.7685197557545083
                ],
                "470": [
                    0.05307567044810236,
                    0.40301328235636485,
                    0.776987476853468
                ],
                "475": [
                    0.05608242876889942,
                    0.44909289531567054,
                    0.7607732845463846
                ],
                "480": [
                    0.05884938333023767,
                    0.4906529510637693,
                    0.7383886138877903
                ],
                "485": [
                    0.0568303997562773,
                    0.5106795980147516,
                    0.6846174985710928
                ],
                "490": [
                    0.05557805781493832,
                    0.539672101159374,
                    0.6282906981161073
                ],
                "495": [
                    0.05739228240408446,
                    0.6045280290785571,
                    0.5617411571079747
                ],
                "500": [
                    0.059206506993230636,
                    0.6693839569977406,
                    0.4951916160998422
                ],
                "505": [
                    0.06714986971772291,
                    0.7508910287539097,
                    0.42306429864990547
                ],
                "510": [
                    0.07509323244221516,
                    0.8323981005100793,
                    0.3509369811999701
                ],
                "515": [
                    0.09356944384393806,
                    0.8801271550945844,
                    0.29095364247912303
                ],
                "520": [
                    0.11204565524566094,
                    0.9278562096790895,
                    0.23097030375827612
                ],
                "525": [
                    0.11757887520933374,
                    0.9522726474822251,
                    0.19697840461664148
                ],
                "530": [
                    0.12311209517300664,
                    0.9766890852853612,
                    0.16298650547500676
                ],
                "535": [
                    0.11635498674235449,
                    0.9942259653114948,
                    0.13457665511263542
                ],
                "540": [
                    0.09323943719687934,
                    0.9928012376603391,
                    0.11493907723552213
                ],
                "545": [
                    0.07843209355806284,
                    0.9568074259620352,
                    0.096898296623861
                ],
                "550": [
                    0.06362474991924627,
                    0.9208136142637318,
                    0.07885751601220015
                ],
                "555": [
                    0.06264926026125667,
                    0.883648163985288,
                    0.06300495928824373
                ],
                "560": [
                    0.06596885521512282,
                    0.8440300724124573,
                    0.050258476176930515
                ],
                "565": [
                    0.0757310770867724,
                    0.8007330188980434,
                    0.04217110348458184
                ],
                "570": [
                    0.1664341469427928,
                    0.7457771886907265,
                    0.037428449272981126
                ],
                "575": [
                    0.31109778212172695,
                    0.6830488406881404,
                    0.03491560738187906
                ],
                "580": [
                    0.4578437984839904,
                    0.6234632615320866,
                    0.03290521078423855
                ],
                "585": [
                    0.6129193395795689,
                    0.5764487577621586,
                    0.032904595360444565
                ],
                "590": [
                    0.7340092797285118,
                    0.521633324644658,
                    0.032397654225999564
                ],
                "595": [
                    0.7191568160909126,
                    0.4356141741368586,
                    0.029865410248950525
                ],
                "600": [
                    0.6966023735035032,
                    0.3521362137001313,
                    0.027196358549129565
                ],
                "605": [
                    0.6432400151168495,
                    0.2788230135476976,
                    0.02398007595822112
                ],
                "610": [
                    0.5927959640924747,
                    0.21784164395364686,
                    0.02135871637753868
                ],
                "615": [
                    0.5467293741115178,
                    0.17535802019717,
                    0.019629741312195272
                ],
                "620": [
                    0.5006627841305605,
                    0.13287439644069318,
                    0.01790076624685181
                ],
                "625": [
                    0.45470877493377293,
                    0.11154684604839311,
                    0.01622046175446603
                ],
                "630": [
                    0.4087547657369852,
                    0.09021929565609288,
                    0.01454015726208026
                ],
                "635": [
                    0.3627468725354758,
                    0.07233015266604996,
                    0.01391964187253753
                ],
                "640": [
                    0.3191016507111281,
                    0.06019531050165259,
                    0.014488832884662092
                ],
                "645": [
                    0.28523041842375935,
                    0.0504472272262943,
                    0.013458114886397473
                ],
                "650": [
                    0.25175499294419595,
                    0.04187357485657811,
                    0.012735644393557798
                ],
                "655": [
                    0.219862794695855,
                    0.03799764610943014,
                    0.01324616392241789
                ],
                "660": [
                    0.1882855150211702,
                    0.034368057270307846,
                    0.013329448779196408
                ],
                "665": [
                    0.15796790964111157,
                    0.031723828063288544,
                    0.011703794947648718
                ],
                "670": [
                    0.11088927799339127,
                    0.024236848299027745,
                    0.008559031999690764
                ],
                "675": [
                    0.03866910694417868,
                    0.009485742698904958,
                    0.003135605377117382
                ],
                "680": [
                    0.010173924003290442,
                    0.003722613899212061,
                    0.0010100096127888944
                ],
                "685": [
                    0.010828733134618518,
                    0.0039514696331390846,
                    0.0010829677539569988
                ],
                "690": [
                    0.008218693496919411,
                    0.0030995235047269745,
                    0.000853866159006645
                ],
                "695": [
                    0.004792441666963498,
                    0.0019773769107300863,
                    0.0005492496300266744
                ],
                "700": [
                    0.001366189837007584,
                    0.0008552303167331969,
                    0.00024463310104670395
                ],
                "705": [
                    0.001162082417847619,
                    0.0007508308311985355,
                    0.00021624940609636404
                ],
                "710": [
                    0.0009579749986876544,
                    0.0006464313456638744,
                    0.0001878657111460239
                ],
                "715": [
                    0.0007538675795276894,
                    0.0005420318601292124,
                    0.00015948201619568378
                ],
                "720": [
                    0.0005497601603677252,
                    0.000437632374594551,
                    0.0001310983212453439
                ],
                "725": [
                    0.00034565274120776043,
                    0.00033323288905988933,
                    0.00010271462629500398
                ],
                "730": [
                    0.00018236680587978892,
                    0.00024971330063216,
                    8.000767033473186e-05
                ],
                "735": [
                    0.00018236680587978887,
                    0.00024971330063216016,
                    8.000767033473186e-05
                ],
                "740": [
                    0.00018236680587978887,
                    0.00024971330063216016,
                    8.000767033473186e-05
                ],
                "745": [
                    0.00018236680587978887,
                    0.00024971330063216016,
                    8.000767033473186e-05
                ],
                "750": [
                    0.00018236680587978887,
                    0.00024971330063216016,
                    8.000767033473186e-05
                ],
                "755": [
                    0.00018236680587978887,
                    0.00024971330063216016,
                    8.000767033473186e-05
                ],
                "760": [
                    0.00018236680587978887,
                    0.00024971330063216016,
                    8.000767033473186e-05
                ],
                "765": [
                    0.00018236680587978887,
                    0.00024971330063216016,
                    8.000767033473186e-05
                ],
                "770": [
                    0.00018236680587978887,
                    0.00024971330063216016,
                    8.000767033473186e-05
                ],
                "775": [
                    0.00018236680587978887,
                    0.00024971330063216016,
                    8.000767033473186e-05
                ],
                "780": [
                    0.00018236680587978892,
                    0.00024971330063216016,
                    8.000767033473186e-05
                ]
            }
        },
        "index": {
            "main": [
                "R",
                "G",
                "B"
            ]
        },
        "reflection_geometry": null,
        "transmission_geometry": null,
        "units": "relative"
    }
}
