{
    "header": {
        "catalog_number": "Sony_ILCE-9_0.1.0",
        "comments": null,
        "description": "camera spectral sensitivity data",
        "document_creation_date": "2025-06-03T10:59:26.392074Z",
        "document_creator": "wetadigital",
        "laboratory": "wetadigital",
        "license": "Apache-2.0",
        "manufacturer": "Sony",
        "measurement_equipment": "lightsaber",
        "model": "ILCE-9",
        "schema_version": "0.1.0",
        "unique_identifier": "eb556267-3aaa-463a-9271-192b29e332ac"
    },
    "spectral_data": {
        "bandwidth_FWHM": null,
        "bandwidth_corrected": null,
        "data": {
            "main": {
                "380": [
                    0.0005942101062454607,
                    0.001271753698438541,
                    0.0005747982948652347
                ],
                "385": [
                    0.0005797562305358059,
                    0.001134112169562788,
                    0.0007214989462611194
                ],
                "390": [
                    0.0005653023548261515,
                    0.000996470640687038,
                    0.0008681995976570029
                ],
                "395": [
                    0.0005508484791164965,
                    0.0008588291118112839,
                    0.0010149002490528834
                ],
                "400": [
                    0.01760389410147723,
                    0.018500901127800593,
                    0.088200962101168
                ],
                "405": [
                    0.034656939723837966,
                    0.036142973143789885,
                    0.17538702395328323
                ],
                "410": [
                    0.06331247949747483,
                    0.07356709436671147,
                    0.3668402435430359
                ],
                "415": [
                    0.07893268787044784,
                    0.10226422622400926,
                    0.5140558255363389
                ],
                "420": [
                    0.07067887247198446,
                    0.11055486024661051,
                    0.5541055146601941
                ],
                "425": [
                    0.06254469161867465,
                    0.1192545129345673,
                    0.5873181944914093
                ],
                "430": [
                    0.05620377727785024,
                    0.12982228942555474,
                    0.6215007133869657
                ],
                "435": [
                    0.05255276270575398,
                    0.14319225162108856,
                    0.6571379908790334
                ],
                "440": [
                    0.04890174813365778,
                    0.15656221381662258,
                    0.692775268371101
                ],
                "445": [
                    0.045052240957372806,
                    0.1722528834103461,
                    0.7299546326643764
                ],
                "450": [
                    0.04115311063004072,
                    0.1885237298536173,
                    0.7675195186579519
                ],
                "455": [
                    0.039307271257857254,
                    0.21815536751585904,
                    0.7783178495582335
                ],
                "460": [
                    0.03746143188567385,
                    0.2477870051781011,
                    0.7891161804585153
                ],
                "465": [
                    0.04063516007340605,
                    0.3058562995493998,
                    0.7839370386951476
                ],
                "470": [
                    0.04380888826113824,
                    0.3639255939206988,
                    0.7787578969317793
                ],
                "475": [
                    0.046363050135683585,
                    0.4045468187974628,
                    0.7556463109348548
                ],
                "480": [
                    0.04876232043193231,
                    0.44080602630059357,
                    0.7280516138795408
                ],
                "485": [
                    0.04666906063696079,
                    0.4570080045103246,
                    0.6770802843981347
                ],
                "490": [
                    0.04547088298678084,
                    0.4841508997759018,
                    0.6237210014190996
                ],
                "495": [
                    0.04785303391576751,
                    0.5550574632648616,
                    0.5608099044495491
                ],
                "500": [
                    0.050235184844754206,
                    0.6259640267538216,
                    0.49789880747999926
                ],
                "505": [
                    0.05793180774867919,
                    0.7107805172424262,
                    0.42518082200703405
                ],
                "510": [
                    0.0656284306526041,
                    0.7955970077310299,
                    0.35246283653406896
                ],
                "515": [
                    0.08352786404298665,
                    0.8630442946096684,
                    0.2959730294765895
                ],
                "520": [
                    0.10142729743336924,
                    0.9304915814883054,
                    0.2394832224191096
                ],
                "525": [
                    0.10622494300876985,
                    0.9572255886081884,
                    0.20463195241999207
                ],
                "530": [
                    0.11102258858417009,
                    0.9839595957280712,
                    0.16978068242087457
                ],
                "535": [
                    0.10385997832203965,
                    0.9970268093956465,
                    0.13905836366446514
                ],
                "540": [
                    0.08050497619082525,
                    0.9821604728418838,
                    0.11517941856954401
                ],
                "545": [
                    0.06414194160846207,
                    0.9375606961166023,
                    0.09390026066432904
                ],
                "550": [
                    0.04777890702609898,
                    0.8929609193913195,
                    0.07262110275911406
                ],
                "555": [
                    0.04453977070203194,
                    0.8372962374026084,
                    0.05454131147387724
                ],
                "560": [
                    0.04524743113991577,
                    0.7822803591976062,
                    0.040100531721279066
                ],
                "565": [
                    0.051875286720725756,
                    0.7282376866681649,
                    0.031118269267638964
                ],
                "570": [
                    0.1298955711647041,
                    0.658016267606926,
                    0.025143904488996272
                ],
                "575": [
                    0.25551080818412736,
                    0.5770090175244912,
                    0.02117480482701862
                ],
                "580": [
                    0.38595251939633185,
                    0.5002321553673349,
                    0.017614374714904978
                ],
                "585": [
                    0.5357001273796617,
                    0.4403768449112956,
                    0.01568862280224732
                ],
                "590": [
                    0.653205383300042,
                    0.3769393830319173,
                    0.013705755966275482
                ],
                "595": [
                    0.6417412309686275,
                    0.29917331545917814,
                    0.011494429437046908
                ],
                "600": [
                    0.6194407761594773,
                    0.22503633181799193,
                    0.009449330221111458
                ],
                "605": [
                    0.5537951114393851,
                    0.1654156839030158,
                    0.00806914025834857
                ],
                "610": [
                    0.49699345962039154,
                    0.119850231502634,
                    0.0070820948285673525
                ],
                "615": [
                    0.4534578271530466,
                    0.0953675723741435,
                    0.006684766198258644
                ],
                "620": [
                    0.4099221946857024,
                    0.07088491324565291,
                    0.0062874375679499404
                ],
                "625": [
                    0.36848098980607275,
                    0.060143232431592517,
                    0.006407206822844801
                ],
                "630": [
                    0.32703978492644264,
                    0.049401551617532125,
                    0.0065269760777396674
                ],
                "635": [
                    0.2841949926400306,
                    0.03980378229658351,
                    0.006749365084597188
                ],
                "640": [
                    0.2419264307853863,
                    0.032551269015824225,
                    0.007139008475090027
                ],
                "645": [
                    0.21038431509850597,
                    0.027816310937150767,
                    0.007581950888348155
                ],
                "650": [
                    0.17968499237972227,
                    0.02351545221158745,
                    0.00792201311354459
                ],
                "655": [
                    0.15235684153332396,
                    0.02095099089846452,
                    0.00785055458649426
                ],
                "660": [
                    0.12583914261176501,
                    0.01859171538329698,
                    0.007663165031022959
                ],
                "665": [
                    0.1025632513895648,
                    0.01705318305995082,
                    0.007012051361867752
                ],
                "670": [
                    0.07882639207769546,
                    0.014956018340082927,
                    0.005998791183725043
                ],
                "675": [
                    0.05439808063132265,
                    0.012020905025432524,
                    0.00444231124210109
                ],
                "680": [
                    0.03312604727258189,
                    0.008330779099943333,
                    0.0028834412313130378
                ],
                "685": [
                    0.013958199305595838,
                    0.004137311433894961,
                    0.0013229778410822567
                ],
                "690": [
                    0.007844434681186339,
                    0.002685498089994424,
                    0.0008216753708521514
                ],
                "695": [
                    0.004994190892420971,
                    0.0019190983266308415,
                    0.0005851631306222141
                ],
                "700": [
                    0.0021439471036556077,
                    0.0011526985632672583,
                    0.0003486508903922768
                ],
                "705": [
                    0.0018026700117578438,
                    0.0009965776282692199,
                    0.0003044219628361837
                ],
                "710": [
                    0.0014613929198600759,
                    0.0008404566932711823,
                    0.0002601930352800905
                ],
                "715": [
                    0.0011201158279623095,
                    0.0006843357582731446,
                    0.00021596410772399806
                ],
                "720": [
                    0.0007788387360645429,
                    0.0005282148232751073,
                    0.00017173518016790502
                ],
                "725": [
                    0.00043756164416677563,
                    0.0003720938882770692,
                    0.00012750625261181208
                ],
                "730": [
                    0.00016453997064856232,
                    0.00024719714027863896,
                    9.212311056693783e-05
                ],
                "735": [
                    0.00016453997064856234,
                    0.00024719714027863896,
                    9.212311056693783e-05
                ],
                "740": [
                    0.00016453997064856234,
                    0.00024719714027863896,
                    9.212311056693783e-05
                ],
                "745": [
                    0.00016453997064856234,
                    0.00024719714027863896,
                    9.212311056693783e-05
                ],
                "750": [
                    0.00016453997064856234,
                    0.00024719714027863896,
                    9.212311056693783e-05
                ],
                "755": [
                    0.00016453997064856234,
                    0.00024719714027863896,
                    9.212311056693783e-05
                ],
                "760": [
                    0.00016453997064856234,
                    0.00024719714027863896,
                    9.212311056693783e-05
                ],
                "765": [
                    0.00016453997064856234,
                    0.00024719714027863896,
                    9.212311056693783e-05
                ],
                "770": [
                    0.00016453997064856234,
                    0.00024719714027863896,
                    9.212311056693783e-05
                ],
                "775": [
                    0.00016453997064856234,
                    0.00024719714027863896,
                    9.212311056693783e-05
                ],
                "780": [
                    0.00016453997064856237,
                    0.0002471971402786389,
                    9.212311056693783e-05
                ]
            }
        },
        "index": {
            "main": [
                "R",
                "G",
                "B"
            ]
        },
        "reflection_geometry": null,
        "transmission_geometry": null,
        "units": "relative"
    }
}